autoevaluator/LLM.py
autoevaluator/__init__.py
autoevaluator/client.py
autoevaluator/eval.py
autoevaluator/eval_v2.py
autoevaluator/simplify.py
autoevaluator-1.1.3.dist-info/METADATA
autoevaluator-1.1.3.dist-info/WHEEL
autoevaluator-1.1.3.dist-info/licenses/LICENSE
autoevaluator-1.1.3.dist-info/RECORD
