Metadata-Version: 2.4
Name: autoevaluator
Version: 1.1.3
Summary: Fully automated LLM evaluator
License-File: LICENSE
Author: Darveen Vijayan
Author-email: +darveenvijayan.27@gmail.com
Requires-Python: >=3.9,<4.0
Classifier: Programming Language :: Python :: 3
Classifier: Programming Language :: Python :: 3.9
Classifier: Programming Language :: Python :: 3.10
Classifier: Programming Language :: Python :: 3.11
Classifier: Programming Language :: Python :: 3.12
Classifier: Programming Language :: Python :: 3.13
Classifier: Programming Language :: Python :: 3.14
Requires-Dist: aioboto3 (>=15.5.0,<16.0.0)
Requires-Dist: anthropic (>=0.76.0,<0.77.0)
Requires-Dist: google-genai (>=1.0.0,<2.0.0)
Requires-Dist: instructor (>=1.5.0,<2.0.0)
Requires-Dist: openai (>=1.51.0,<2.0.0)
Requires-Dist: python-dotenv (>=1.0.0,<2.0.0)
Requires-Dist: typing-extensions (>=4.12.2,<5.0.0)
